pkglite/__init__.py
pkglite/classify.py
pkglite/cli.py
pkglite/main.py
pkglite/pack.py
pkglite/unpack.py
pkglite/use.py
pkglite/templates/__init__.py
pkglite/templates/pkgliteignore.txt
pkglite-0.1.8.dist-info/METADATA
pkglite-0.1.8.dist-info/WHEEL
pkglite-0.1.8.dist-info/entry_points.txt
pkglite-0.1.8.dist-info/licenses/LICENSE
pkglite-0.1.8.dist-info/licenses/LICENSES_THIRD_PARTY
pkglite-0.1.8.dist-info/RECORD
