Metadata-Version: 2.4
Name: pkglite
Version: 0.1.8
Summary: Pack and unpack source projects of any language into portable text files
Project-URL: Homepage, https://pharmaverse.github.io/py-pkglite/
Project-URL: Documentation, https://pharmaverse.github.io/py-pkglite/
Project-URL: Repository, https://github.com/pharmaverse/py-pkglite
Project-URL: Issues, https://github.com/pharmaverse/py-pkglite/issues
Project-URL: Changelog, https://github.com/pharmaverse/py-pkglite/blob/main/CHANGELOG.md
Author-email: Nan Xiao <nan.xiao1@msd.com>
License-File: LICENSE
License-File: LICENSES_THIRD_PARTY
Classifier: Development Status :: 3 - Alpha
Classifier: Intended Audience :: Developers
Classifier: Intended Audience :: Healthcare Industry
Classifier: Intended Audience :: Information Technology
Classifier: Intended Audience :: Science/Research
Classifier: License :: OSI Approved :: MIT License
Classifier: Operating System :: OS Independent
Classifier: Programming Language :: Python :: 3
Classifier: Programming Language :: Python :: 3.10
Classifier: Programming Language :: Python :: 3.11
Classifier: Programming Language :: Python :: 3.12
Classifier: Programming Language :: Python :: 3.13
Classifier: Programming Language :: Python :: 3.14
Classifier: Topic :: Software Development :: Build Tools
Classifier: Topic :: System :: Archiving :: Packaging
Classifier: Typing :: Typed
Requires-Python: >=3.10
Requires-Dist: pathspec>=0.12.1
Requires-Dist: rich>=13.9.4
Requires-Dist: typer>=0.12.5
